data_cleaner.py
fastest_time_print_jhlong-1.0.2.dist-info/METADATA
fastest_time_print_jhlong-1.0.2.dist-info/WHEEL
fastest_time_print_jhlong-1.0.2.dist-info/top_level.txt
fastest_time_print_jhlong-1.0.2.dist-info/RECORD
