Metadata-Version: 2.1
Name: fastest_time_print_jhlong
Version: 1.0.2
Summary: 这个函数可以帮助你进行清洗数据，标准化、去重排序、最后切片打印的功能
Author: jhlong
Author-email: jhlong2024@163.com
